srmhga/__init__.py
srmhga/py.typed
srmhga/stack.py
srmhga/adapters/__init__.py
srmhga/adapters/langchain.py
srmhga/adapters/llamaindex.py
srmhga/aqsrl/__init__.py
srmhga/aqsrl/aqsrl.py
srmhga/aqsrl/config.py
srmhga/aqsrl/layer.py
srmhga/consolidation/__init__.py
srmhga/consolidation/extractor.py
srmhga/consolidation/pipeline.py
srmhga/core/__init__.py
srmhga/core/config.py
srmhga/core/exceptions.py
srmhga/core/types.py
srmhga/core/utils.py
srmhga/dv/__init__.py
srmhga/dv/base.py
srmhga/dv/sqlite_vault.py
srmhga/embeddings/__init__.py
srmhga/embeddings/base.py
srmhga/embeddings/providers.py
srmhga/forgetting/__init__.py
srmhga/forgetting/forget.py
srmhga/forgetting/salience.py
srmhga/metrics/__init__.py
srmhga/metrics/sink.py
srmhga/pm/__init__.py
srmhga/pm/profile_memory.py
srmhga/triage/__init__.py
srmhga/triage/sensitivity.py
srmhga/triage/triage.py
srmhga-1.0.0.dist-info/licenses/LICENSE
srmhga-1.0.0.dist-info/METADATA
srmhga-1.0.0.dist-info/WHEEL
srmhga-1.0.0.dist-info/top_level.txt
srmhga-1.0.0.dist-info/RECORD
